html5lib_typogrify/__init__.py
html5lib_typogrify/french/__init__.py
html5lib_typogrify/french/filters/__init__.py
html5lib_typogrify/french/filters/dashes.py
html5lib_typogrify/french/filters/ellipsis.py
html5lib_typogrify/french/filters/figures.py
html5lib_typogrify/french/filters/hyphenate.py
html5lib_typogrify/french/filters/medor.py
html5lib_typogrify/french/filters/spaces.py
html5lib_typogrify/french/filters/widows_orphans.py
html5lib_typogrify-0.3.1.dist-info/METADATA
html5lib_typogrify-0.3.1.dist-info/WHEEL
html5lib_typogrify-0.3.1.dist-info/top_level.txt
html5lib_typogrify-0.3.1.dist-info/RECORD
