Metadata-Version: 2.1
Name: html5lib_typogrify
Version: 0.3.1
Summary: Corrects common typographical mistakes.
Home-page: https://gitlab.com/medor/html5lib_typogrify
Author: Alexandre Leray
Author-email: alexandre@stdin.fr
Classifier: Development Status :: 2 - Pre-Alpha
Classifier: Environment :: Web Environment
Classifier: Intended Audience :: Developers
Classifier: License :: OSI Approved :: GNU Affero General Public License v3 or later (AGPLv3+)
Classifier: Operating System :: OS Independent
Classifier: Programming Language :: Python
Classifier: Programming Language :: Python :: 3
Classifier: Programming Language :: Python :: 3.3
Classifier: Programming Language :: Python :: 3.4
Classifier: Programming Language :: Python :: 3.5
Classifier: Programming Language :: Python :: 3.6
Classifier: Topic :: Text Processing :: Filters
Classifier: Topic :: Text Processing :: Markup :: HTML
Requires-Dist: html5lib <1.2,>=1.0.1
Requires-Dist: Pyphen <1.15,>=0.9.5
